{"name":"build-javascript","namedChunkGroups":{"app":{"name":"app","assets":[{"name":"webpack-runtime-a9e7edd39670edb8395d.js","size":3711},{"name":"framework-11e9a391e21e89cdc36e.js","size":140769},{"name":"styles.fc4206d18a09e88f57a6.css","size":74},{"name":"app-4fcbd383ad8feed623dc.js","size":106919}],"filteredAssets":0,"assetsSize":251473,"filteredAuxiliaryAssets":3,"auxiliaryAssetsSize":810491},"component---src-pages-404-mdx":{"name":"component---src-pages-404-mdx","assets":[{"name":"commons-aecde8c44f9983b597c4.js","size":111121},{"name":"component---src-pages-404-mdx-305c3cff7dbe93d9718c.js","size":923}],"filteredAssets":0,"assetsSize":112044,"filteredAuxiliaryAssets":2,"auxiliaryAssetsSize":616252},"component---src-pages-blog-mdx":{"name":"component---src-pages-blog-mdx","assets":[{"name":"commons-aecde8c44f9983b597c4.js","size":111121},{"name":"component---src-pages-blog-mdx-903675c822a7df3f1711.js","size":448}],"filteredAssets":0,"assetsSize":111569,"filteredAuxiliaryAssets":2,"auxiliaryAssetsSize":614763},"component---src-pages-index-mdx":{"name":"component---src-pages-index-mdx","assets":[{"name":"commons-aecde8c44f9983b597c4.js","size":111121},{"name":"component---src-pages-index-mdx-06b879d389cd3b0131d3.js","size":1675}],"filteredAssets":0,"assetsSize":112796,"filteredAuxiliaryAssets":2,"auxiliaryAssetsSize":618398}},"assetsByChunkName":{"app":["webpack-runtime-a9e7edd39670edb8395d.js","framework-11e9a391e21e89cdc36e.js","styles.fc4206d18a09e88f57a6.css","app-4fcbd383ad8feed623dc.js"],"component---src-pages-404-mdx":["commons-aecde8c44f9983b597c4.js","component---src-pages-404-mdx-305c3cff7dbe93d9718c.js"],"component---src-pages-blog-mdx":["commons-aecde8c44f9983b597c4.js","component---src-pages-blog-mdx-903675c822a7df3f1711.js"],"component---src-pages-index-mdx":["commons-aecde8c44f9983b597c4.js","component---src-pages-index-mdx-06b879d389cd3b0131d3.js"]},"childAssetsByChunkName":{}}